fichub_api/__init__.py
fichub_api/py.typed
fichub_api-0.2.2.dist-info/LICENSE
fichub_api-0.2.2.dist-info/METADATA
fichub_api-0.2.2.dist-info/WHEEL
fichub_api-0.2.2.dist-info/top_level.txt
fichub_api-0.2.2.dist-info/RECORD
