Metadata-Version: 2.1
Name: fichub-api
Version: 0.2.2
Summary: A small asynchronous wrapper for the FicHub API, made to retrieve story metadata and download stories from various websites.
Author-email: Sachaa-Thanasius <111999343+Sachaa-Thanasius@users.noreply.github.com>
License: MIT License
Project-URL: Homepage, https://github.com/Sachaa-Thanasius/fichub-api
Project-URL: Bug Tracker, https://github.com/Sachaa-Thanasius/fichub-api/issues
Keywords: python,python-3,fichub,webfiction-metadata
Classifier: Development Status :: 3 - Alpha
Classifier: Framework :: aiohttp
Classifier: License :: OSI Approved :: MIT License
Classifier: Natural Language :: English
Classifier: Operating System :: OS Independent
Classifier: Programming Language :: Python :: 3 :: Only
Classifier: Programming Language :: Python :: 3.8
Classifier: Programming Language :: Python :: 3.9
Classifier: Programming Language :: Python :: 3.10
Classifier: Programming Language :: Python :: 3.11
Classifier: Topic :: Internet
Classifier: Topic :: Software Development :: Libraries
Classifier: Topic :: Software Development :: Libraries :: Python Modules
Classifier: Topic :: Utilities
Classifier: Typing :: Typed
Requires-Python: >=3.8
License-File: LICENSE
Requires-Dist: aiohttp >=3.8
Requires-Dist: msgspec
